inclusion_block_tag/__init__.py
inclusion_block_tag/apps.py
inclusion_block_tag/inclusion_block_tag.py
inclusion_block_tag/models.py
django_inclusion_block_tag-0.2.3.dist-info/AUTHORS.rst
django_inclusion_block_tag-0.2.3.dist-info/LICENSE
django_inclusion_block_tag-0.2.3.dist-info/METADATA
django_inclusion_block_tag-0.2.3.dist-info/WHEEL
django_inclusion_block_tag-0.2.3.dist-info/top_level.txt
django_inclusion_block_tag-0.2.3.dist-info/RECORD
