Metadata-Version: 2.1
Name: django-inclusion-block-tag
Version: 0.2.3
Summary: Your project description goes here
Home-page: https://github.com/bmihelac/django-inclusion-block-tag
Author: Bojan Mihelac
Author-email: bmihelac@mihelac.org
License: MIT
Keywords: django-inclusion-block-tag
Platform: UNKNOWN
Classifier: Development Status :: 3 - Alpha
Classifier: Framework :: Django :: 2.0
Classifier: Intended Audience :: Developers
Classifier: License :: OSI Approved :: BSD License
Classifier: Natural Language :: English
Classifier: Programming Language :: Python :: 2
Classifier: Programming Language :: Python :: 2.7
Classifier: Programming Language :: Python :: 3
Classifier: Programming Language :: Python :: 3.4
Classifier: Programming Language :: Python :: 3.5
Classifier: Programming Language :: Python :: 3.6
Requires-Dist: Django (>=2.0)
